namecrement/__init__.py
namecrement/core.py
namecrement-0.1.0.dist-info/licenses/LICENSE
namecrement-0.1.0.dist-info/METADATA
namecrement-0.1.0.dist-info/WHEEL
namecrement-0.1.0.dist-info/top_level.txt
namecrement-0.1.0.dist-info/RECORD
