Metadata-Version: 2.4
Name: namecrement
Version: 0.1.0
Summary: A smart python utility that generates unique incremental names, preventing naming collisions by automatically appending incremental suffixes.
Author-email: Hichem Taboukouyout <hichem.taboukouyout@hichemtab-tech.me>
License: MIT
Project-URL: Homepage, https://github.com/HichemTab-tech/Namecrement-py
Project-URL: Repository, https://github.com/HichemTab-tech/Namecrement-py
Requires-Python: >=3.8
License-File: LICENSE
Dynamic: license-file
